{
  "_class": "group",
  "do_objectID": "68EEC773-331B-4228-88B5-4AB3150F5732",
  "exportOptions": {
    "_class": "exportOptions",
    "exportFormats": [
    ],
    "includedLayerIds": [
    ],
    "layerOptions": 0,
    "shouldTrim": false
  },
  "frame": {
    "_class": "rect",
    "constrainProportions": false,
    "height": 36,
    "width": 866,
    "x": 0,
    "y": 26
  },
  "hasClickThrough": false,
  "isFlippedHorizontal": false,
  "isFlippedVertical": false,
  "isLocked": false,
  "isVisible": true,
  "layerListExpandedType": 0,
  "layers": [
    {
      "class": "shapeGroup",
      "id": "372FFB37-0B3F-46B8-B8A1-53F21191E9B5"
    },
    {
      "class": "text",
      "id": "E62B2204-A005-4490-8899-04A2728B05F7"
    }
  ],
  "name": "Input / Text (Placeholder)",
  "nameIsFixed": false,
  "resizingConstraint": 63,
  "resizingType": 0,
  "rotation": 0,
  "shouldBreakMaskChain": false,
  "style": {
    "_class": "style",
    "endDecorationType": 0,
    "miterLimit": 10,
    "startDecorationType": 0
  }
}