{
  "_class": "symbolInstance",
  "do_objectID": "554AFC2C-54ED-481D-A3D0-B4BCF3BB6F22",
  "exportOptions": {
    "_class": "exportOptions",
    "do_objectID": "DE082589-07B4-4BC9-B538-7A1FC7D77C10",
    "exportFormats": [
    ],
    "includedLayerIds": [
    ],
    "layerOptions": 0,
    "shouldTrim": false
  },
  "frame": {
    "_class": "rect",
    "constrainProportions": false,
    "do_objectID": "16ADB3C9-A6EA-4786-B253-99DDFB142C36",
    "height": 19,
    "width": 400,
    "x": 0,
    "y": 0
  },
  "horizontalSpacing": 0,
  "isFlippedHorizontal": false,
  "isFlippedVertical": false,
  "isLocked": false,
  "isVisible": true,
  "layerListExpandedType": 0,
  "name": "Checkbox / Unchecked Copy",
  "nameIsFixed": false,
  "overrideValues": [
    {
      "_class": "overrideValue",
      "do_objectID": "F72B3752-0EC8-4BC8-A44C-850B0455675B",
      "overrideName": "88004E03-25D2-4FC2-97B8-09545590739E_stringValue",
      "value": "Select All"
    }
  ],
  "overrides": {
    "88004E03-25D2-4FC2-97B8-09545590739E": "Select All"
  },
  "resizingConstraint": 63,
  "resizingType": 0,
  "rotation": 0,
  "scale": 1,
  "shouldBreakMaskChain": false,
  "style": {
    "_class": "style",
    "do_objectID": "99A0EDB3-8296-4FAF-9BA5-D8D2244267FD",
    "endDecorationType": 0,
    "miterLimit": 10,
    "startDecorationType": 0
  },
  "symbolID": "81BC068D-30A4-4C17-8F3B-DC54CEF52CC1",
  "verticalSpacing": 0
}