{
  "_class": "shapeGroup",
  "clippingMaskMode": 0,
  "do_objectID": "FDD6F266-2130-4D50-8105-6FB0C35250E6",
  "exportOptions": {
    "_class": "exportOptions",
    "do_objectID": "55A0F0E4-EA57-44E6-B16D-A71B16471CE8",
    "exportFormats": [
    ],
    "includedLayerIds": [
    ],
    "layerOptions": 0,
    "shouldTrim": false
  },
  "frame": {
    "_class": "rect",
    "constrainProportions": false,
    "do_objectID": "8CCA844C-B88A-49BC-A9BF-561FF27683D0",
    "height": 36,
    "width": 540,
    "x": 0,
    "y": 0
  },
  "hasClickThrough": false,
  "hasClippingMask": false,
  "isFlippedHorizontal": false,
  "isFlippedVertical": false,
  "isLocked": false,
  "isVisible": true,
  "layerListExpandedType": 0,
  "layers": [
    {
      "class": "rectangle",
      "id": "E14123A0-F9ED-40BD-9C78-713419E5709E"
    }
  ],
  "name": "Input Background",
  "nameIsFixed": true,
  "originalObjectID": "DFEEFEF8-3A7F-4451-AF91-C8A578243A00",
  "resizingConstraint": 63,
  "resizingType": 0,
  "rotation": 0,
  "shouldBreakMaskChain": false,
  "style": {
    "_class": "style",
    "borders": [
      {
        "_class": "border",
        "color": {
          "_class": "color",
          "alpha": 1,
          "blue": 0.6666666666666666,
          "green": 0.6627450980392157,
          "red": 0.6666666666666666
        },
        "fillType": 0,
        "isEnabled": true,
        "position": 1,
        "thickness": 2
      }
    ],
    "do_objectID": "3487771B-EC4A-45FC-9D2D-DA23B9837B32",
    "endDecorationType": 0,
    "fills": [
      {
        "_class": "fill",
        "color": {
          "_class": "color",
          "alpha": 1,
          "blue": 1,
          "green": 0.9999365210533142,
          "red": 1
        },
        "fillType": 0,
        "isEnabled": true,
        "noiseIndex": 0,
        "noiseIntensity": 0,
        "patternFillType": 0,
        "patternTileScale": 1
      }
    ],
    "innerShadows": [
      {
        "_class": "innerShadow",
        "blurRadius": 3,
        "color": {
          "_class": "color",
          "alpha": 0.5,
          "blue": 0,
          "green": 0,
          "red": 0
        },
        "contextSettings": {
          "_class": "graphicsContextSettings",
          "blendMode": 0,
          "opacity": 1
        },
        "isEnabled": false,
        "offsetX": 0,
        "offsetY": 1,
        "spread": 0
      }
    ],
    "miterLimit": 10,
    "sharedObjectID": "E981F8DD-40D3-4425-8F2B-7C48C474A327",
    "startDecorationType": 0
  },
  "windingRule": 1
}