{
  "_class": "group",
  "do_objectID": "2B8D8D3D-6078-4D67-89F7-C69733347E3D",
  "exportOptions": {
    "_class": "exportOptions",
    "exportFormats": [
    ],
    "includedLayerIds": [
    ],
    "layerOptions": 0,
    "shouldTrim": false
  },
  "frame": {
    "_class": "rect",
    "constrainProportions": false,
    "height": 144,
    "width": 639,
    "x": 165,
    "y": 195
  },
  "hasClickThrough": false,
  "isFlippedHorizontal": false,
  "isFlippedVertical": false,
  "isLocked": false,
  "isVisible": true,
  "layerListExpandedType": 0,
  "layers": [
    {
      "class": "text",
      "id": "83FF549E-F8C2-4E4E-A93B-3F911B481AF8"
    },
    {
      "class": "text",
      "id": "CB852310-BE58-45DC-BD1B-F75A826CEF6F"
    }
  ],
  "name": "grp_banner",
  "nameIsFixed": true,
  "resizingConstraint": 63,
  "resizingType": 0,
  "rotation": 0,
  "shouldBreakMaskChain": false,
  "style": {
    "_class": "style",
    "endDecorationType": 0,
    "miterLimit": 10,
    "startDecorationType": 0
  }
}