{
  "_class": "group",
  "do_objectID": "60B41D6A-D195-4B95-9879-21CF451CAFF5",
  "exportOptions": {
    "_class": "exportOptions",
    "exportFormats": [
    ],
    "includedLayerIds": [
    ],
    "layerOptions": 0,
    "shouldTrim": false
  },
  "frame": {
    "_class": "rect",
    "constrainProportions": false,
    "height": 647,
    "width": 890,
    "x": 30,
    "y": 2225
  },
  "hasClickThrough": false,
  "isFlippedHorizontal": false,
  "isFlippedVertical": false,
  "isLocked": false,
  "isVisible": true,
  "layerListExpandedType": 2,
  "layers": [
    {
      "class": "shapeGroup",
      "id": "FD0FB3CF-7CDF-4800-8DAB-8A723A20B329"
    },
    {
      "class": "text",
      "id": "C96509DD-C25B-4A66-AA1B-030EB746D33E"
    },
    {
      "class": "text",
      "id": "CE4B455D-2027-485C-99BA-591ECF3B1E78"
    },
    {
      "class": "group",
      "id": "521D94E7-9331-4507-83DA-E05C3F270759"
    },
    {
      "class": "group",
      "id": "65BB624E-D20D-4BE5-941D-947DA64C939E"
    },
    {
      "class": "group",
      "id": "302C5777-4377-4B19-A091-A4CB4F4CBE3D"
    },
    {
      "class": "group",
      "id": "B58D7929-BAA8-43F5-98D7-DE2E7AFA36C1"
    },
    {
      "class": "group",
      "id": "DB62D31A-B9FC-415D-82CC-91243997B80D"
    },
    {
      "class": "text",
      "id": "5552B097-62E2-4DA2-B2F9-BB25A10D6597"
    }
  ],
  "name": "grp_coverage-form",
  "nameIsFixed": true,
  "resizingConstraint": 63,
  "resizingType": 0,
  "rotation": 0,
  "shouldBreakMaskChain": false,
  "style": {
    "_class": "style",
    "endDecorationType": 0,
    "miterLimit": 10,
    "shadows": [
      {
        "_class": "shadow",
        "blurRadius": 4,
        "color": {
          "_class": "color",
          "alpha": 1,
          "blue": 0.4,
          "green": 0.4,
          "red": 0.4
        },
        "contextSettings": {
          "_class": "graphicsContextSettings",
          "blendMode": 0,
          "opacity": 1
        },
        "isEnabled": false,
        "offsetX": 0,
        "offsetY": 2,
        "spread": 0
      }
    ],
    "startDecorationType": 0
  }
}