{
  "_class": "group",
  "do_objectID": "B1427936-3E80-488A-BA5E-2D2C5B0CDF4C",
  "exportOptions": {
    "_class": "exportOptions",
    "do_objectID": "977982E0-358D-4D2F-8BE5-2EA6CFB055E1",
    "exportFormats": [
    ],
    "includedLayerIds": [
    ],
    "layerOptions": 0,
    "shouldTrim": false
  },
  "frame": {
    "_class": "rect",
    "constrainProportions": false,
    "do_objectID": "61C85487-C7B4-4C1D-8850-BCA049247682",
    "height": 305,
    "width": 866,
    "x": 1,
    "y": 46
  },
  "hasClickThrough": false,
  "isFlippedHorizontal": false,
  "isFlippedVertical": false,
  "isLocked": false,
  "isVisible": true,
  "layerListExpandedType": 2,
  "layers": [
    {
      "class": "symbolInstance",
      "id": "01C15A41-24F6-40A5-B02D-1C9B9D5896B0"
    },
    {
      "class": "symbolInstance",
      "id": "578C7923-98DE-40C1-9702-34E9449C06FE"
    },
    {
      "class": "symbolInstance",
      "id": "A88D2E7F-CF2D-4FD0-B447-38DCF3AB6962"
    },
    {
      "class": "shapeGroup",
      "id": "E490857B-642F-42BC-9BC6-A9D0BE97F963"
    }
  ],
  "name": "rules-list",
  "nameIsFixed": true,
  "resizingConstraint": 63,
  "resizingType": 0,
  "rotation": 0,
  "shouldBreakMaskChain": false,
  "style": {
    "_class": "style",
    "do_objectID": "AF98DC43-C537-4C61-BB05-7F936A142E0E",
    "endDecorationType": 0,
    "miterLimit": 10,
    "startDecorationType": 0
  }
}