{
  "_class": "shapeGroup",
  "clippingMaskMode": 0,
  "do_objectID": "1CE5AC81-62A4-4029-9483-26D169EB8286",
  "exportOptions": {
    "_class": "exportOptions",
    "do_objectID": "C3387F35-06F0-4EB4-B3F2-6D30AFD11FD6",
    "exportFormats": [
    ],
    "includedLayerIds": [
    ],
    "layerOptions": 0,
    "shouldTrim": false
  },
  "frame": {
    "_class": "rect",
    "constrainProportions": false,
    "do_objectID": "A2843DA3-FD00-4153-9392-7FEA54D3B98E",
    "height": 5,
    "width": 9,
    "x": 0,
    "y": 11
  },
  "hasClickThrough": false,
  "hasClippingMask": false,
  "isFlippedHorizontal": false,
  "isFlippedVertical": false,
  "isLocked": false,
  "isVisible": true,
  "layerListExpandedType": 0,
  "layers": [
    {
      "class": "shapePath",
      "id": "44012660-7FBD-4E47-AF07-766D2B73BFF0"
    }
  ],
  "name": "Triangle",
  "nameIsFixed": true,
  "resizingConstraint": 63,
  "resizingType": 0,
  "rotation": 0,
  "shouldBreakMaskChain": false,
  "style": {
    "_class": "style",
    "blur": {
      "_class": "blur",
      "center": "{0.5, 0.5}",
      "do_objectID": "42EE79A6-DA8D-4FC3-B32E-7B422C2E3786",
      "isEnabled": false,
      "motionAngle": 0,
      "radius": 6.48,
      "type": 0
    },
    "borders": [
      {
        "_class": "border",
        "color": {
          "_class": "color",
          "alpha": 1,
          "blue": 0.592,
          "green": 0.592,
          "red": 0.592
        },
        "fillType": 0,
        "isEnabled": false,
        "position": 0,
        "thickness": 0.6480000000000001
      }
    ],
    "do_objectID": "B2934E4F-5CCA-4C89-AA66-92063AC98DB1",
    "endDecorationType": 0,
    "fills": [
      {
        "_class": "fill",
        "color": {
          "_class": "color",
          "alpha": 1,
          "blue": 0.2,
          "green": 0.2,
          "red": 0.2
        },
        "fillType": 0,
        "isEnabled": true,
        "noiseIndex": 0,
        "noiseIntensity": 0,
        "patternFillType": 1,
        "patternTileScale": 1
      }
    ],
    "miterLimit": 10,
    "sharedObjectID": "C20A1548-8AC1-49D0-8DE1-74556B3950F1",
    "startDecorationType": 0
  },
  "windingRule": 1
}