{
  "_class": "symbolInstance",
  "do_objectID": "15629DB9-F344-4EC8-9E04-366456C9CA76",
  "exportOptions": {
    "_class": "exportOptions",
    "do_objectID": "62809D6A-9ABA-4476-A20C-B02E64AB78A2",
    "exportFormats": [
    ],
    "includedLayerIds": [
    ],
    "layerOptions": 0,
    "shouldTrim": false
  },
  "frame": {
    "_class": "rect",
    "constrainProportions": false,
    "do_objectID": "2D2B3221-297A-4A2C-B4CB-9B343D002846",
    "height": 24,
    "width": 24,
    "x": 9,
    "y": 0
  },
  "horizontalSpacing": 0,
  "isFlippedHorizontal": false,
  "isFlippedVertical": false,
  "isLocked": false,
  "isVisible": true,
  "layerListExpandedType": 0,
  "name": "Icons / layout-component",
  "nameIsFixed": false,
  "overrideValues": [
  ],
  "overrides": {
  },
  "resizingConstraint": 63,
  "resizingType": 0,
  "rotation": 0,
  "scale": 1,
  "shouldBreakMaskChain": false,
  "style": {
    "_class": "style",
    "do_objectID": "32FB458F-3713-453C-9127-36452524B5AE",
    "endDecorationType": 0,
    "miterLimit": 10,
    "startDecorationType": 0
  },
  "symbolID": "561D4235-EEB5-4872-A485-307DE6191263",
  "verticalSpacing": 0
}