{
  "_class": "symbolInstance",
  "do_objectID": "E2C25053-4B61-4E4B-9292-3024C75D59FE",
  "exportOptions": {
    "_class": "exportOptions",
    "do_objectID": "992B9609-123E-4C5E-93A3-037A41206452",
    "exportFormats": [
    ],
    "includedLayerIds": [
    ],
    "layerOptions": 0,
    "shouldTrim": false
  },
  "frame": {
    "_class": "rect",
    "constrainProportions": false,
    "do_objectID": "8E4A5BF1-00E1-4FA2-8F21-2526AD443DB2",
    "height": 19,
    "width": 200,
    "x": 0,
    "y": 289
  },
  "horizontalSpacing": 0,
  "isFlippedHorizontal": false,
  "isFlippedVertical": false,
  "isLocked": false,
  "isVisible": true,
  "layerListExpandedType": 0,
  "name": "Checkbox / Unchecked Copy",
  "nameIsFixed": false,
  "overrideValues": [
    {
      "_class": "overrideValue",
      "overrideName": "4A868392-AA27-4190-806C-D0B8AE5F1D00_stringValue",
      "value": "Required"
    }
  ],
  "overrides": {
    "4A868392-AA27-4190-806C-D0B8AE5F1D00": "Required"
  },
  "resizingConstraint": 63,
  "resizingType": 0,
  "rotation": 0,
  "scale": 1,
  "shouldBreakMaskChain": false,
  "style": {
    "_class": "style",
    "do_objectID": "55552D82-0D26-4D2E-B42F-7E71F361566E",
    "endDecorationType": 0,
    "miterLimit": 10,
    "startDecorationType": 0
  },
  "symbolID": "18DBAD74-3045-4BEC-A3F3-419893DE450C",
  "verticalSpacing": 0
}